psyplot_gui/__init__.py
psyplot_gui/_version.py
psyplot_gui/backend.py
psyplot_gui/common.py
psyplot_gui/console.py
psyplot_gui/content_widget.py
psyplot_gui/dataframeeditor.py
psyplot_gui/dependencies.py
psyplot_gui/fmt_widget.py
psyplot_gui/help_explorer.py
psyplot_gui/main.py
psyplot_gui/plot_creator.py
psyplot_gui/preferences.py
psyplot_gui/compat/__init__.py
psyplot_gui/compat/qtcompat.py
psyplot_gui/config/__init__.py
psyplot_gui/config/rcsetup.py
psyplot_gui/icons/console-go.png
psyplot_gui/icons/console-go.png.license
psyplot_gui/icons/console-go.svg
psyplot_gui/icons/console-go.svg.license
psyplot_gui/icons/copy.png
psyplot_gui/icons/copy.png.license
psyplot_gui/icons/copy.svg
psyplot_gui/icons/copy.svg.license
psyplot_gui/icons/docu_button.png
psyplot_gui/icons/docu_button.png.license
psyplot_gui/icons/docu_button.svg
psyplot_gui/icons/docu_button.svg.license
psyplot_gui/icons/info.png
psyplot_gui/icons/info.png.license
psyplot_gui/icons/info.svg
psyplot_gui/icons/info.svg.license
psyplot_gui/icons/invalid.png
psyplot_gui/icons/invalid.png.license
psyplot_gui/icons/invalid.svg
psyplot_gui/icons/invalid.svg.license
psyplot_gui/icons/ipython_console.png
psyplot_gui/icons/ipython_console.png.license
psyplot_gui/icons/ipython_console_t.png
psyplot_gui/icons/ipython_console_t.png.license
psyplot_gui/icons/lock.png
psyplot_gui/icons/lock.png.license
psyplot_gui/icons/lock.svg
psyplot_gui/icons/lock.svg.license
psyplot_gui/icons/lock_open.png
psyplot_gui/icons/lock_open.png.license
psyplot_gui/icons/lock_open.svg
psyplot_gui/icons/lock_open.svg.license
psyplot_gui/icons/logo.png
psyplot_gui/icons/logo.png.license
psyplot_gui/icons/logo.svg
psyplot_gui/icons/logo.svg.license
psyplot_gui/icons/minus.png
psyplot_gui/icons/minus.png.license
psyplot_gui/icons/minus.svg
psyplot_gui/icons/minus.svg.license
psyplot_gui/icons/minusminus.png
psyplot_gui/icons/minusminus.png.license
psyplot_gui/icons/minusminus.svg
psyplot_gui/icons/minusminus.svg.license
psyplot_gui-1.5.0.dist-info/CC-BY-4.0.txt
psyplot_gui-1.5.0.dist-info/CC0-1.0.txt
psyplot_gui-1.5.0.dist-info/LGPL-3.0-only.txt
psyplot_gui-1.5.0.dist-info/METADATA
psyplot_gui-1.5.0.dist-info/WHEEL
psyplot_gui-1.5.0.dist-info/top_level.txt
psyplot_gui-1.5.0.dist-info/RECORD
